mdb_engine/README.md
mdb_engine/__init__.py
mdb_engine/config.py
mdb_engine/constants.py
mdb_engine/dependencies.py
mdb_engine/exceptions.py
mdb_engine/auth/ARCHITECTURE.md
mdb_engine/auth/README.md
mdb_engine/auth/__init__.py
mdb_engine/auth/audit.py
mdb_engine/auth/base.py
mdb_engine/auth/casbin_factory.py
mdb_engine/auth/casbin_models.py
mdb_engine/auth/config_defaults.py
mdb_engine/auth/config_helpers.py
mdb_engine/auth/cookie_utils.py
mdb_engine/auth/csrf.py
mdb_engine/auth/decorators.py
mdb_engine/auth/dependencies.py
mdb_engine/auth/helpers.py
mdb_engine/auth/integration.py
mdb_engine/auth/jwt.py
mdb_engine/auth/middleware.py
mdb_engine/auth/oso_factory.py
mdb_engine/auth/provider.py
mdb_engine/auth/rate_limiter.py
mdb_engine/auth/restrictions.py
mdb_engine/auth/session_manager.py
mdb_engine/auth/shared_middleware.py
mdb_engine/auth/shared_users.py
mdb_engine/auth/token_lifecycle.py
mdb_engine/auth/token_store.py
mdb_engine/auth/users.py
mdb_engine/auth/utils.py
mdb_engine/auth/websocket_sessions.py
mdb_engine/cli/__init__.py
mdb_engine/cli/main.py
mdb_engine/cli/utils.py
mdb_engine/cli/commands/__init__.py
mdb_engine/cli/commands/generate.py
mdb_engine/cli/commands/migrate.py
mdb_engine/cli/commands/show.py
mdb_engine/cli/commands/validate.py
mdb_engine/core/README.md
mdb_engine/core/__init__.py
mdb_engine/core/app_registration.py
mdb_engine/core/app_secrets.py
mdb_engine/core/connection.py
mdb_engine/core/encryption.py
mdb_engine/core/engine.py
mdb_engine/core/index_management.py
mdb_engine/core/manifest.py
mdb_engine/core/ray_integration.py
mdb_engine/core/seeding.py
mdb_engine/core/service_initialization.py
mdb_engine/core/types.py
mdb_engine/database/README.md
mdb_engine/database/__init__.py
mdb_engine/database/abstraction.py
mdb_engine/database/connection.py
mdb_engine/database/query_validator.py
mdb_engine/database/resource_limiter.py
mdb_engine/database/scoped_wrapper.py
mdb_engine/di/__init__.py
mdb_engine/di/container.py
mdb_engine/di/providers.py
mdb_engine-0.6.0.dist-info/licenses/LICENSE
mdb_engine-0.6.0.dist-info/METADATA
mdb_engine-0.6.0.dist-info/WHEEL
mdb_engine-0.6.0.dist-info/entry_points.txt
mdb_engine-0.6.0.dist-info/top_level.txt
mdb_engine-0.6.0.dist-info/RECORD
