Metadata-Version: 2.4
Name: mdb-engine
Version: 0.6.0
Summary: MongoDB Engine
Home-page: https://github.com/ranfysvalle02/mdb-engine
Author: Fabian Valle
Author-email: Fabian Valle <oblivio.company@gmail.com>
License: AGPL-3.0
Project-URL: Homepage, https://github.com/ranfysvalle02/mdb-engine
Project-URL: Documentation, https://github.com/ranfysvalle02/mdb-engine#readme
Project-URL: Repository, https://github.com/ranfysvalle02/mdb-engine
Project-URL: Issues, https://github.com/ranfysvalle02/mdb-engine/issues
Keywords: mongodb,runtime,engine,database,scoping
Classifier: Development Status :: 4 - Beta
Classifier: Intended Audience :: Developers
Classifier: License :: OSI Approved :: GNU Affero General Public License v3 or later (AGPLv3+)
Classifier: Programming Language :: Python :: 3
Classifier: Programming Language :: Python :: 3.10
Classifier: Programming Language :: Python :: 3.11
Classifier: Programming Language :: Python :: 3.12
Classifier: Topic :: Database
Classifier: Topic :: Software Development :: Libraries :: Python Modules
Requires-Python: >=3.10
License-File: LICENSE
Requires-Dist: motor>=3.0.0
Requires-Dist: pymongo>=4.0.0
Requires-Dist: fastapi>=0.100.0
Requires-Dist: pydantic>=2.0.0
Requires-Dist: pyjwt>=2.8.0
Requires-Dist: jsonschema>=4.0.0
Requires-Dist: bcrypt>=4.0.0
Requires-Dist: cryptography>=41.0.0
Requires-Dist: mem0ai>=0.1.7
Requires-Dist: semantic-text-splitter>=0.9.0
Requires-Dist: numpy<2.0.0,>=1.0.0
Requires-Dist: openai>=1.0.0
Requires-Dist: azure-identity>=1.15.0
Requires-Dist: click>=8.0.0
Provides-Extra: casbin
Requires-Dist: casbin>=1.0.0; extra == "casbin"
Requires-Dist: casbin-motor-adapter>=0.1.0; extra == "casbin"
Provides-Extra: oso
Requires-Dist: oso-cloud>=0.1.0; extra == "oso"
Provides-Extra: llm
Provides-Extra: test
Requires-Dist: pytest>=7.4.0; extra == "test"
Requires-Dist: pytest-asyncio>=0.21.0; extra == "test"
Requires-Dist: pytest-cov>=4.1.0; extra == "test"
Requires-Dist: pytest-mock>=3.11.0; extra == "test"
Requires-Dist: pytest-timeout>=2.1.0; extra == "test"
Requires-Dist: pytest-xdist>=3.3.0; extra == "test"
Requires-Dist: testcontainers>=3.7.0; extra == "test"
Provides-Extra: dev
Requires-Dist: ruff<0.6.0,>=0.4.0; extra == "dev"
Requires-Dist: semgrep>=1.50.0; extra == "dev"
Provides-Extra: all
Requires-Dist: casbin>=1.0.0; extra == "all"
Requires-Dist: casbin-motor-adapter>=0.1.0; extra == "all"
Requires-Dist: oso-cloud>=0.1.0; extra == "all"
Dynamic: author
Dynamic: home-page
Dynamic: license-file
Dynamic: requires-python
